Day 2/dff.v
module dff(input clk, input d, output reg q);

always @(posedge clk) begin
    q <= d;
end

endmodule

Day 2/tb_dff.v
module tb_dff;

reg clk, d;
wire q;

dff uut (
    .clk(clk),
    .d(d),
    .q(q)
);

initial begin
    $dumpfile("dff.vcd");
    $dumpvars(0, tb_dff);

    clk = 0;
    d = 0;

    #10 d = 1;
    #10 d = 0;
    #10 d = 1;
    #10 d = 0;

    #10 $finish;
end

always #5 clk = ~clk;

endmodule

Day 2/dff.vcd
$date
	Mon Sep 14 06:02:45 2026
$end
$version
	Icarus Verilog
$end
$timescale
	1s
$end
$scope module tb_dff $end
$var wire 1 ! q $end
$var reg 1 " clk $end
$var reg 1 # d $end
$scope module uut $end
$var wire 1 " clk $end
$var wire 1 # d $end
$var reg 1 ! q $end
$upscope $end
$upscope $end
$enddefinitions $end
#0
$dumpvars
0#
0"
x!
$end
#5
0!
1"
#10
0"
1#
#15
1!
1"
#20
0"
0#
#25
0!
1"
#30
0"
1#
#35
1!
1"
#40
0"
0#
#45
0!
1"
