Day 2/dff_async.v
module dff_async(input clk, input reset, input d, output reg q);

always @(posedge clk or posedge reset) begin
    if (reset)
        q <= 1'b0;
    else
        q <= d;
end

endmodule

Day 2/tb_dff_async.v
module tb_dff_async;

reg clk, reset, d;
wire q;

dff_async uut (
    .clk(clk),
    .reset(reset),
    .d(d),
    .q(q)
);

initial begin
    $dumpfile("dff_async.vcd");
    $dumpvars(0, tb_dff_async);

    clk = 0;
    reset = 1;
    d = 0;

    #10 reset = 0;
    #10 d = 1;
    #10 d = 0;
    #10 reset = 1;
    #10 reset = 0;
    #10 d = 1;

    #10 $finish;
end

always #5 clk = ~clk;

endmodule

Day 2/dff_async.vcd
$date
	Mon Sep 14 06:16:14 2026
$end
$version
	Icarus Verilog
$end
$timescale
	1s
$end
$scope module tb_dff_async $end
$var wire 1 ! q $end
$var reg 1 " clk $end
$var reg 1 # d $end
$var reg 1 $ reset $end
$scope module uut $end
$var wire 1 " clk $end
$var wire 1 # d $end
$var wire 1 $ reset $end
$var reg 1 ! q $end
$upscope $end
$upscope $end
$enddefinitions $end
#0
$dumpvars
1$
0#
0"
0!
$end
#5
1"
#10
0"
0$
#15
1"
#20
0"
1#
#25
1!
1"
#30
0"
0#
#35
0!
1"
#40
0"
1$
#45
1"
#50
0"
0$
#55
1"
#60
0"
1#
#65
1!
1"
